httpx_auth/__init__.py
httpx_auth/_authentication.py
httpx_auth/_aws.py
httpx_auth/_errors.py
httpx_auth/py.typed
httpx_auth/testing.py
httpx_auth/version.py
httpx_auth/_oauth2/__init__.py
httpx_auth/_oauth2/authentication_responses_server.py
httpx_auth/_oauth2/authorization_code.py
httpx_auth/_oauth2/authorization_code_pkce.py
httpx_auth/_oauth2/browser.py
httpx_auth/_oauth2/client_credentials.py
httpx_auth/_oauth2/common.py
httpx_auth/_oauth2/implicit.py
httpx_auth/_oauth2/resource_owner_password.py
httpx_auth/_oauth2/tokens.py
httpx_auth-0.23.0.dist-info/LICENSE
httpx_auth-0.23.0.dist-info/METADATA
httpx_auth-0.23.0.dist-info/WHEEL
httpx_auth-0.23.0.dist-info/top_level.txt
httpx_auth-0.23.0.dist-info/RECORD
