Metadata-Version: 2.1
Name: httpx_auth
Version: 0.23.0
Summary: Authentication for HTTPX
Author-email: Colin Bounouar <colin.bounouar.dev@gmail.com>
Maintainer-email: Colin Bounouar <colin.bounouar.dev@gmail.com>
License: MIT License
Project-URL: documentation, https://colin-b.github.io/httpx_auth/
Project-URL: repository, https://github.com/Colin-b/httpx_auth
Project-URL: changelog, https://github.com/Colin-b/httpx_auth/blob/master/CHANGELOG.md
Project-URL: issues, https://github.com/Colin-b/httpx_auth/issues
Keywords: authentication,oauth2,aws,okta,aad,entra
Classifier: Development Status :: 5 - Production/Stable
Classifier: Intended Audience :: Developers
Classifier: License :: OSI Approved :: MIT License
Classifier: Natural Language :: English
Classifier: Typing :: Typed
Classifier: Programming Language :: Python
Classifier: Programming Language :: Python :: 3
Classifier: Programming Language :: Python :: 3.9
Classifier: Programming Language :: Python :: 3.10
Classifier: Programming Language :: Python :: 3.11
Classifier: Programming Language :: Python :: 3.12
Classifier: Programming Language :: Python :: 3.13
Classifier: Topic :: Software Development :: Build Tools
Requires-Python: >=3.9
License-File: LICENSE
Requires-Dist: httpx==0.28.*
Provides-Extra: testing
Requires-Dist: pyjwt==2.*; extra == "testing"
Requires-Dist: pytest_httpx==0.35.*; extra == "testing"
Requires-Dist: time-machine==2.*; extra == "testing"
Requires-Dist: pytest-cov==6.*; extra == "testing"
Requires-Dist: pytest-asyncio==0.25.*; extra == "testing"
